{
  "kind": "youtube#searchListResponse",
  "etag": "o5KdDxUxOI2_tPGRxafiRqhHyv0",
  "nextPageToken": "CBkQAA",
  "regionCode": "US",
  "pageInfo": {
    "totalResults": 101,
    "resultsPerPage": 25
  },
  "items": [
    {
      "kind": "youtube#searchResult",
      "etag": "lFTrPBCHK4yhNicHxwtg9ttfkNw",
      "id": {
        "kind": "youtube#video",
        "videoId": "fLclGPr7fj4"
      },
      "snippet": {
        "publishedAt": "2009-11-20T06:47:57Z",
        "channelId": "UCQ28fSp1FaTRCLhtDDSI0Bg",
        "title": "Tillman the Skateboarding Bulldog Skates, Skimboards, and SURFS!!",
        "description": "The Famous Tillman the Skateboarding Bulldog skateboards, skimboards, and SURFS!  Amazing what he can do.  For more Tillman videos, check out www.jonespets.tv",
        "thumbnails": {
          "default": {
            "url": "https://i.ytimg.com/vi/fLclGPr7fj4/default.jpg",
            "width": 120,
            "height": 90
          },
          "medium": {
            "url": "https://i.ytimg.com/vi/fLclGPr7fj4/mqdefault.jpg",
            "width": 320,
            "height": 180
          },
          "high": {
            "url": "https://i.ytimg.com/vi/fLclGPr7fj4/hqdefault.jpg",
            "width": 480,
            "height": 360
          }
        },
        "channelTitle": "ron davis",
        "liveBroadcastContent": "none",
        "publishTime": "2009-11-20T06:47:57Z"
      }
    },
    {
      "kind": "youtube#searchResult",
      "etag": "CU9oZMfdHKp3vGRKSv6KOx1WB7o",
      "id": {
        "kind": "youtube#video",
        "videoId": "BkD2nN5275c"
      },
      "snippet": {
        "publishedAt": "2020-02-19T20:21:38Z",
        "channelId": "UC09IvZwjpunzrdHH1EHok-w",
        "title": "🤣 Funniest 🐶 Dogs and 😻 Cats - Awesome Funny Pet Animals Videos 😇",
        "description": "Enjoy new funniest and very cute compilation of the week about try not laugh funny animals' life video. But some cats in this video will actually surprise you!\nAnd you can enjoy they in this video. Cats are surely the most popular pets and awesome animals nowadays. Dogs are awesome animals. Despite all their differences, they have much in common, too.  And yet, there are dogs that resemble none of their kin in the whole world.\nAll their breeds differ by size, features, and color, temperament.  \n\n\n\nThanks for wonderful music by Vexento - \"Digital Hug\"\nhttps://www.youtube.com/user/Vexento",
        "thumbnails": {
          "default": {
            "url": "https://i.ytimg.com/vi/BkD2nN5275c/default.jpg",
            "width": 120,
            "height": 90
          },
          "medium": {
            "url": "https://i.ytimg.com/vi/BkD2nN5275c/mqdefault.jpg",
            "width": 320,
            "height": 180
          },
          "high": {
            "url": "https://i.ytimg.com/vi/BkD2nN5275c/hqdefault.jpg",
            "width": 480,
            "height": 360
          },
          "standard": {
            "url": "https://i.ytimg.com/vi/BkD2nN5275c/sddefault.jpg",
            "width": 640,
            "height": 480
          },
          "maxres": {
            "url": "https://i.ytimg.com/vi/BkD2nN5275c/maxresdefault.jpg",
            "width": 1280,
            "height": 720
          }
        },
        "channelTitle": "Funny Animals' Life",
        "liveBroadcastContent": "none",
        "publishTime": "2020-02-19T20:21:38Z"
      }
    },
    {
      "kind": "youtube#searchResult",
      "etag": "QWi_Bv1zTj9uUqzcXTFrCbXXOGY",
      "id": {
        "kind": "youtube#video",
        "videoId": "00WeVRH1VaY"
      },
      "snippet": {
        "publishedAt": "2020-04-05T13:35:27Z",
        "channelId": "UCQPcUCNJupSdjUwBYrQQ8dQ",
        "title": "TOP 10 Skateboarding Dogs",
        "description": "Teespring Merch: http://teespring.com/en-GB/stores/laugh-at-dogs\nSupport / Donate: http://www.buymeacoffee.com/laughatdogs\r\n\nThe best & coolest dogs who skateboard...........\n\n#skateboarddog #skateboardingdogs\n\nWelcome to LAUGH AT DOGS… The Home of Fun Dog Videos & Dog Training Tips. Hit ‘SUBSCRIBE’ and tap the ‘Bell’ icon to be notified when a new video is uploaded\n\nTHE TOP 10\n1. Cartman the skateboarding dog visits Amsterdam\nhttps://www.youtube.com/watch?v=NeYPI9045xw\n2. Amazing French Bulldog Rocks On Skateboard\nhttps://www.youtube.com/watch?reload=9&v=gdJhY3iLUTQ\n3. MURDY THE DAWG \"BARK AND DESTROY\"\nhttps://www.youtube.com/watch?v=jrWTqG9KZ00\n4. TWIG SKATES FORT LAUDERDALE - SPRING BREAK - Skateboarding Dog\nhttps://www.youtube.com/watch?v=l-o32te-fME\n5. Eric the skateboarding dog - Welcome to the team!\nhttps://www.youtube.com/watch?v=qbwGOan2FRg\n6. Jumpy Extreme skateboarder dog\nhttps://www.youtube.com/watch?v=YexLt6ZM-08\n7. Skateboarding Dog on Hulu Future man\nhttps://www.youtube.com/watch?v=fnmrHg5_54s\n8. Skateboarding Dog - HD Redux\nhttps://www.youtube.com/watch?reload=9&v=R8XAlSp838Y\n9. Dog Loves To Go To The Skate Park With His Dad | The Dodo\nhttps://www.youtube.com/watch?reload=9&v=Ej95hRv-xNM\n10. Otto the skateboarding bulldog - Guinness World Records\nhttps://www.youtube.com/watch?reload=9&v=EVnzXA9b7Ww\n\nMUSIC FEATURED\nOpening Sequence\nSerious Beatz – Next Level\nClosing Sequence\nSong: Tritonal - Getaway (ft. Angel Taylor) (Koven Remix)",
        "thumbnails": {
          "default": {
            "url": "https://i.ytimg.com/vi/00WeVRH1VaY/default.jpg",
            "width": 120,
            "height": 90
          },
          "medium": {
            "url": "https://i.ytimg.com/vi/00WeVRH1VaY/mqdefault.jpg",
            "width": 320,
            "height": 180
          },
          "high": {
            "url": "https://i.ytimg.com/vi/00WeVRH1VaY/hqdefault.jpg",
            "width": 480,
            "height": 360
          },
          "standard": {
            "url": "https://i.ytimg.com/vi/00WeVRH1VaY/sddefault.jpg",
            "width": 640,
            "height": 480
          },
          "maxres": {
            "url": "https://i.ytimg.com/vi/00WeVRH1VaY/maxresdefault.jpg",
            "width": 1280,
            "height": 720
          }
        },
        "channelTitle": "LAUGH AT DOGS",
        "liveBroadcastContent": "none",
        "publishTime": "2020-04-05T13:35:27Z"
      }
    },
    {
      "kind": "youtube#searchResult",
      "etag": "Ho3CuZ70LI0HUbyyI3WDuHUqQTU",
      "id": {
        "kind": "youtube#video",
        "videoId": "EVnzXA9b7Ww"
      },
      "snippet": {
        "publishedAt": "2015-11-12T10:01:53Z",
        "channelId": "UCeSRjhfeeqIgr--AcP9qhyg",
        "title": "Otto the skateboarding bulldog - Guinness World Records",
        "description": "► Subscribe for more || http://bit.ly/GWR-Subscribe\n► Watch the GWR’s Favourites || http://bit.ly/GWR-Favs\n\nThe longest human tunnel traveled through by a dog skateboarder is 30 people and was achieved by Otto the Skateboarding Bulldog in Lima, Peru, on November 8 2015. Read full story: http://bit.ly/GWR-SkateboardingDog\n\n----------------------------------------------------------------------------------------------\n\nAt Guinness World Records we want to show that everyone in the world is the best at something, and we’re here to measure it! Whether you’ve got the stretchiest skin, know the world’s smallest dog or want to create the largest human dominoes chain we want to hear about it. \n\nHere on the Guinness World Records YouTube channel we want to showcase incredible talent. If you're looking for videos featuring the world's tallest, shortest, fastest, longest, oldest and most incredible things on the planet, you're in the right place.\n\n----------------------------------------------------------------------------------------------\n\nWebsite || http://bit.ly/GWR-Website\nFacebook || http://bit.ly/GWR-FB\nTwitter || http://bit.ly/GWR-TW\nInstagram || http://bit.ly/GWR-Insta\nSnapchat || http://bit.ly/GWR-SC\nTikTok || http://bit.ly/GWR-TT\n\n#GWR #GuinnessWorldRecords #worldrecord",
        "thumbnails": {
          "default": {
            "url": "https://i.ytimg.com/vi/EVnzXA9b7Ww/default.jpg",
            "width": 120,
            "height": 90
          },
          "medium": {
            "url": "https://i.ytimg.com/vi/EVnzXA9b7Ww/mqdefault.jpg",
            "width": 320,
            "height": 180
          },
          "high": {
            "url": "https://i.ytimg.com/vi/EVnzXA9b7Ww/hqdefault.jpg",
            "width": 480,
            "height": 360
          },
          "standard": {
            "url": "https://i.ytimg.com/vi/EVnzXA9b7Ww/sddefault.jpg",
            "width": 640,
            "height": 480
          },
          "maxres": {
            "url": "https://i.ytimg.com/vi/EVnzXA9b7Ww/maxresdefault.jpg",
            "width": 1280,
            "height": 720
          }
        },
        "channelTitle": "Guinness World Records",
        "liveBroadcastContent": "none",
        "publishTime": "2015-11-12T10:01:53Z"
      }
    },
    {
      "kind": "youtube#searchResult",
      "etag": "GjWYZ8Y52qzD0PuHqXD9Fz9FhZA",
      "id": {
        "kind": "youtube#video",
        "videoId": "tDOM-U7uStM"
      },
      "snippet": {
        "publishedAt": "2015-05-07T16:55:15Z",
        "channelId": "UC9fD1YzP97mOg-KjXSuCQ2g",
        "title": "Surfing Dogs",
        "description": "We were so stoked to be at the Unleashed by Petco Surfing Dog Competition that happened in Huntington beach. \n\nThis was a fun hot summer day with dogs, kids, food and lots of waves. \n\nThe event also takes place in Imperial Beach, which we've also attended before. The Imperial Beach event is the original surf dog competition. \n\nCheck our video on that:\n\nhttps://www.youtube.com/watch?v=xW-nzM8DcLY\n\nwww.towerpaddleboards.com\nwww.towermade.com",
        "thumbnails": {
          "default": {
            "url": "https://i.ytimg.com/vi/tDOM-U7uStM/default.jpg",
            "width": 120,
            "height": 90
          },
          "medium": {
            "url": "https://i.ytimg.com/vi/tDOM-U7uStM/mqdefault.jpg",
            "width": 320,
            "height": 180
          },
          "high": {
            "url": "https://i.ytimg.com/vi/tDOM-U7uStM/hqdefault.jpg",
            "width": 480,
            "height": 360
          },
          "standard": {
            "url": "https://i.ytimg.com/vi/tDOM-U7uStM/sddefault.jpg",
            "width": 640,
            "height": 480
          },
          "maxres": {
            "url": "https://i.ytimg.com/vi/tDOM-U7uStM/maxresdefault.jpg",
            "width": 1280,
            "height": 720
          }
        },
        "channelTitle": "Tower Beach Club",
        "liveBroadcastContent": "none",
        "publishTime": "2015-05-07T16:55:15Z"
      }
    },
    {
      "kind": "youtube#searchResult",
      "etag": "b6YKyk2RqYSKUCiG_Yg10JBr68I",
      "id": {
        "kind": "youtube#video",
        "videoId": "go6s6xSVMB0"
      },
      "snippet": {
        "publishedAt": "2020-09-14T17:02:25Z",
        "channelId": "UCeSRjhfeeqIgr--AcP9qhyg",
        "title": "Fastest skateboarding dog - Guinness World Records",
        "description": "► Watch the GWR’s Favourites || http://bit.ly/GWR-Favs\n▶ Order Guinness World Records 2021 || https://bit.ly/GWR-2021\n\nJumpy uses various different modes of transport but loves skateboarding the most! He featured on this episode of Officially Amazing with trainer Omar Von Muller, who has trained dogs for movies such as The Artist!\n\nWhether you want to push yourself to the limit, or you have simply discovered a new passion or talent during lockdown, see if you can make it a world record on #GWRDay: http://bit.ly/GWRDay\n----------------------------------------------------------------------------------------------\n\nAt Guinness World Records we want to show that everyone in the world is the best at something, and we’re here to measure it! Whether you’ve got the stretchiest skin, know the world’s smallest dog or want to create the largest human dominoes chain we want to hear about it. \n\nHere on the Guinness World Records YouTube channel we want to showcase incredible talent. If you're looking for videos featuring the world's tallest, shortest, fastest, longest, oldest and most incredible things on the planet, you're in the right place.\n\n----------------------------------------------------------------------------------------------\n\nWebsite || http://bit.ly/GWR-Website\nFacebook || http://bit.ly/GWR-FB\nTwitter || http://bit.ly/GWR-TW\nInstagram || http://bit.ly/GWR-Insta\nSnapchat || http://bit.ly/GWR-SC\nTikTok || http://bit.ly/GWR-TT\n\nFor licensing: tv@guinnessworldrecords.com\n\n#GWR #GuinnessWorldRecords #WorldRecords",
        "thumbnails": {
          "default": {
            "url": "https://i.ytimg.com/vi/go6s6xSVMB0/default.jpg",
            "width": 120,
            "height": 90
          },
          "medium": {
            "url": "https://i.ytimg.com/vi/go6s6xSVMB0/mqdefault.jpg",
            "width": 320,
            "height": 180
          },
          "high": {
            "url": "https://i.ytimg.com/vi/go6s6xSVMB0/hqdefault.jpg",
            "width": 480,
            "height": 360
          },
          "standard": {
            "url": "https://i.ytimg.com/vi/go6s6xSVMB0/sddefault.jpg",
            "width": 640,
            "height": 480
          },
          "maxres": {
            "url": "https://i.ytimg.com/vi/go6s6xSVMB0/maxresdefault.jpg",
            "width": 1280,
            "height": 720
          }
        },
        "channelTitle": "Guinness World Records",
        "liveBroadcastContent": "none",
        "publishTime": "2020-09-14T17:02:25Z"
      }
    },
    {
      "kind": "youtube#searchResult",
      "etag": "tZsjUajWUFE3pZX6ooGrkbb0sI4",
      "id": {
        "kind": "youtube#video",
        "videoId": "bnFHk22yJWo"
      },
      "snippet": {
        "publishedAt": "2021-03-15T04:32:57Z",
        "channelId": "UCIqWFhsJm2VU1ZuGrZnx3Pw",
        "title": "Angry Pets Compilation : Funny Angry Dogs of The Week",
        "description": "Angry Pets Compilation \"Funny Angry Dogs of The Week\n\nThanks For Watching  ! Please Like Share & Comment If You Like This Video ! \r\nSubscribe for new video https://goo.gl/tmB86v\r\n----------------------------------------------------------------------------\r\nAmazing playlist video on MAIPM Channel:\r\n\r\nFunny And Cute Video Baby ➞ http://bit.ly/FunnyAndCuteVideoBaby\r\nDog Video Funny ➞ http://bit.ly/DogVideoFunny\r\nNew Funny Cat Videos ➞ http://bit.ly/NewFunnyCatVideos\r\nCute Bull Dogs ➞ http://bit.ly/CuteBullDogs\r\nFunnyVideoAnimals ➞http://bit.ly/FunnyVideoAnimals\r\n\r\n----------------------------------------------------------------------------\r\n\r\nFollow me :\r\n* Tumblr : https://www.tumblr.com/blog/maipm1102\r\n\r\n* Pinterest : https://www.pinterest.com/MaiPM1102/\r\n\r\n* Twiter : https://twitter.com/BestFunny2X\r\n\r\n* Facebook : https://www.facebook.com/Animal-lovers-Communication-1684665418434610/?fref=ts\r\n\r\n---------------------------------------------------------------------------\r\nCOPYRIGHT ISSUES:\r\nOur purpose, when making COMPILATIONS, is NOT to steal other people's videos, but to share those in quality compilation with other people.\r\nOne of our videos was shared by the owner and allowed for use or we purchased. Some videos we have not contacted the owner. If any owner of clips, used in our compilation, has a copyright issue, feel free to contact us by [ http://3sanimals.com/CopyrightIssues ] . We will remove the clip, video or come to an agreement. Thank you.\r\nUsing or sharing our compilations is allowed, so feel free to share it anywhere, but it would be nice, to use direct link of video, not of copies. Thanks.\r\nYou can also share your pet videos here: http://3sanimals.com/SubmitVideoYourPet\r\n\r\n---------------------------------------------------------------------------\r\n#funnydogs #angrydogs #funnydogreaction \nP/s: Thanks for watching video ! Don't forget subscribe my channel \r\n➞ https://goo.gl/tmB86v",
        "thumbnails": {
          "default": {
            "url": "https://i.ytimg.com/vi/bnFHk22yJWo/default.jpg",
            "width": 120,
            "height": 90
          },
          "medium": {
            "url": "https://i.ytimg.com/vi/bnFHk22yJWo/mqdefault.jpg",
            "width": 320,
            "height": 180
          },
          "high": {
            "url": "https://i.ytimg.com/vi/bnFHk22yJWo/hqdefault.jpg",
            "width": 480,
            "height": 360
          },
          "standard": {
            "url": "https://i.ytimg.com/vi/bnFHk22yJWo/sddefault.jpg",
            "width": 640,
            "height": 480
          },
          "maxres": {
            "url": "https://i.ytimg.com/vi/bnFHk22yJWo/maxresdefault.jpg",
            "width": 1280,
            "height": 720
          }
        },
        "channelTitle": "MAI PM",
        "liveBroadcastContent": "none",
        "publishTime": "2021-03-15T04:32:57Z"
      }
    },
    {
      "kind": "youtube#searchResult",
      "etag": "UgfPqO8yc-3roN1GT3dIt4paDiU",
      "id": {
        "kind": "youtube#video",
        "videoId": "Jrp80wxg5L4"
      },
      "snippet": {
        "publishedAt": "2016-08-15T16:05:52Z",
        "channelId": "UCgHP7d2yix8NwFiQNEgL0MA",
        "title": "Buddha Bulldog SKATER",
        "description": "São Paulo, Brazil! Minhocão Park \n\nFollow: \nfb.com/BuddhaBulldog\nInstagram.com/buda.bulldog \n\n#Love, Buddha.",
        "thumbnails": {
          "default": {
            "url": "https://i.ytimg.com/vi/Jrp80wxg5L4/default.jpg",
            "width": 120,
            "height": 90
          },
          "medium": {
            "url": "https://i.ytimg.com/vi/Jrp80wxg5L4/mqdefault.jpg",
            "width": 320,
            "height": 180
          },
          "high": {
            "url": "https://i.ytimg.com/vi/Jrp80wxg5L4/hqdefault.jpg",
            "width": 480,
            "height": 360
          },
          "standard": {
            "url": "https://i.ytimg.com/vi/Jrp80wxg5L4/sddefault.jpg",
            "width": 640,
            "height": 480
          }
        },
        "channelTitle": "Thiago Iglesias",
        "liveBroadcastContent": "none",
        "publishTime": "2016-08-15T16:05:52Z"
      }
    },
    {
      "kind": "youtube#searchResult",
      "etag": "mEsspQaAOwRyt65fSa2FSIUFMLk",
      "id": {
        "kind": "youtube#video",
        "videoId": "yFynHUn80L0"
      },
      "snippet": {
        "publishedAt": "2010-12-03T17:32:46Z",
        "channelId": "UCWPyv9pf_vt-2PRdq-kgUYA",
        "title": "Tillman",
        "description": "Watch Tillman the skateboarding dog as he does a show outside the Pet Extreme store in Pacific Grove, CA!",
        "thumbnails": {
          "default": {
            "url": "https://i.ytimg.com/vi/yFynHUn80L0/default.jpg",
            "width": 120,
            "height": 90
          },
          "medium": {
            "url": "https://i.ytimg.com/vi/yFynHUn80L0/mqdefault.jpg",
            "width": 320,
            "height": 180
          },
          "high": {
            "url": "https://i.ytimg.com/vi/yFynHUn80L0/hqdefault.jpg",
            "width": 480,
            "height": 360
          }
        },
        "channelTitle": "PetExtremeTV",
        "liveBroadcastContent": "none",
        "publishTime": "2010-12-03T17:32:46Z"
      }
    },
    {
      "kind": "youtube#searchResult",
      "etag": "QJGPX_lUypEhP46tejtMKCS1Llw",
      "id": {
        "kind": "youtube#video",
        "videoId": "vYyUb_MI7to"
      },
      "snippet": {
        "publishedAt": "2015-02-27T01:18:06Z",
        "channelId": "UCqhnX4jA0A5paNd1v-zEysw",
        "title": "GoPro: Didga the Skateboarding Cat",
        "description": "Didga the skateboarding cat from Australia shows off her skills at a local skate park.\n\nFor more of Didga check out:\nhttps://www.youtube.com/c/catmantoo\n\nShot 100% on the HERO3+® camera from \u202ahttp://GoPro.com.\n\nGet stoked and subscribe: http://goo.gl/HgVXpQ\n\nMusic\nNickodemus \"A Beirut Minute\" Inst\nLink to buy: http://goo.gl/0fFzRF",
        "thumbnails": {
          "default": {
            "url": "https://i.ytimg.com/vi/vYyUb_MI7to/default.jpg",
            "width": 120,
            "height": 90
          },
          "medium": {
            "url": "https://i.ytimg.com/vi/vYyUb_MI7to/mqdefault.jpg",
            "width": 320,
            "height": 180
          },
          "high": {
            "url": "https://i.ytimg.com/vi/vYyUb_MI7to/hqdefault.jpg",
            "width": 480,
            "height": 360
          },
          "standard": {
            "url": "https://i.ytimg.com/vi/vYyUb_MI7to/sddefault.jpg",
            "width": 640,
            "height": 480
          },
          "maxres": {
            "url": "https://i.ytimg.com/vi/vYyUb_MI7to/maxresdefault.jpg",
            "width": 1280,
            "height": 720
          }
        },
        "channelTitle": "GoPro",
        "liveBroadcastContent": "none",
        "publishTime": "2015-02-27T01:18:06Z"
      }
    },
    {
      "kind": "youtube#searchResult",
      "etag": "s8MYweKzo-Lz-vG901v31npCnNM",
      "id": {
        "kind": "youtube#video",
        "videoId": "Ek_QZVGUesM"
      },
      "snippet": {
        "publishedAt": "2015-01-18T09:24:32Z",
        "channelId": "UCarZUVvh1vXHDIICZ9KNSOQ",
        "title": "Ultimate Skateboarding Dog Compilation",
        "description": "Gear up for the Ultimate Skateboarding Dog Compilation! Top skateboarding dawgs from across the World doing what they do best! The Ollie. The Half-Pipe. The Carve. It's all here bro! Crank it up and get stoked for these awesome skateboarding dogs! Watch some of the most talented skateboarding dogs in the World show off their hottest moves! Watch these extreme dawgs crank it up as they are super stoked bro! ",
        "thumbnails": {
          "default": {
            "url": "https://i.ytimg.com/vi/Ek_QZVGUesM/default.jpg",
            "width": 120,
            "height": 90
          },
          "medium": {
            "url": "https://i.ytimg.com/vi/Ek_QZVGUesM/mqdefault.jpg",
            "width": 320,
            "height": 180
          },
          "high": {
            "url": "https://i.ytimg.com/vi/Ek_QZVGUesM/hqdefault.jpg",
            "width": 480,
            "height": 360
          },
          "standard": {
            "url": "https://i.ytimg.com/vi/Ek_QZVGUesM/sddefault.jpg",
            "width": 640,
            "height": 480
          }
        },
        "channelTitle": "Comedy For Profit",
        "liveBroadcastContent": "none",
        "publishTime": "2015-01-18T09:24:32Z"
      }
    },
    {
      "kind": "youtube#searchResult",
      "etag": "WLEM3rtitGbLLaWEWYcqbSY45Fk",
      "id": {
        "kind": "youtube#video",
        "videoId": "H7PjyEG5-1U"
      },
      "snippet": {
        "publishedAt": "2018-03-03T21:13:20Z",
        "channelId": "UCm4UUMMt_OmV2TgvbeaXGgw",
        "title": "NINJA CATS vs DOGS - Who Wins?",
        "description": "Funny brave cats and kitties vs dogs. What do you think who will win??\nAnimalzTV in Internet:\nPlease Subscribe: http://goo.gl/O97FCe\nLike us on Facebook: https://www.facebook.com/animalztv4u\nFollow on Twitter: https://twitter.com/AnimalzTVv\nAdd in circles on Google plus: https://plus.google.com/b/109357051925508382516/+AnimalzTV/posts\nVisit our Website: http://www.animalztv.net/ or Submit your videos here: http://www.animalztv.net/submit-video/\n\nCopyright Disclaimer:\nWe Respect other people's Copyrights. We use videoclips with the permission of the authors of original videos to make our compilations. \nBut If you see your clip in our compilation and which you did not submit to http://www.animalztv.net/submit-video/ , it seems, we received false permissions to use this clip. We would be happy to resolve this for you! Please send us a short message about the issue at contact (at) animalztv.net",
        "thumbnails": {
          "default": {
            "url": "https://i.ytimg.com/vi/H7PjyEG5-1U/default.jpg",
            "width": 120,
            "height": 90
          },
          "medium": {
            "url": "https://i.ytimg.com/vi/H7PjyEG5-1U/mqdefault.jpg",
            "width": 320,
            "height": 180
          },
          "high": {
            "url": "https://i.ytimg.com/vi/H7PjyEG5-1U/hqdefault.jpg",
            "width": 480,
            "height": 360
          },
          "standard": {
            "url": "https://i.ytimg.com/vi/H7PjyEG5-1U/sddefault.jpg",
            "width": 640,
            "height": 480
          },
          "maxres": {
            "url": "https://i.ytimg.com/vi/H7PjyEG5-1U/maxresdefault.jpg",
            "width": 1280,
            "height": 720
          }
        },
        "channelTitle": "Animalz TV",
        "liveBroadcastContent": "none",
        "publishTime": "2018-03-03T21:13:20Z"
      }
    },
    {
      "kind": "youtube#searchResult",
      "etag": "_8XCuhlCzyK3NmlF6QwS-MeO3ks",
      "id": {
        "kind": "youtube#video",
        "videoId": "yn-TfAzobDI"
      },
      "snippet": {
        "publishedAt": "2019-05-30T14:31:29Z",
        "channelId": "UCMaHobSU33-_hCM6ASjGNZQ",
        "title": "Raw Run || Race Against the Storm",
        "description": "13th raw run in the series. Subscribe for more! Instagram: @joshneuman\nFilm: @jake_from_skatefarm",
        "thumbnails": {
          "default": {
            "url": "https://i.ytimg.com/vi/yn-TfAzobDI/default.jpg",
            "width": 120,
            "height": 90
          },
          "medium": {
            "url": "https://i.ytimg.com/vi/yn-TfAzobDI/mqdefault.jpg",
            "width": 320,
            "height": 180
          },
          "high": {
            "url": "https://i.ytimg.com/vi/yn-TfAzobDI/hqdefault.jpg",
            "width": 480,
            "height": 360
          },
          "standard": {
            "url": "https://i.ytimg.com/vi/yn-TfAzobDI/sddefault.jpg",
            "width": 640,
            "height": 480
          },
          "maxres": {
            "url": "https://i.ytimg.com/vi/yn-TfAzobDI/maxresdefault.jpg",
            "width": 1280,
            "height": 720
          }
        },
        "channelTitle": "Josh Neuman",
        "liveBroadcastContent": "none",
        "publishTime": "2019-05-30T14:31:29Z"
      }
    },
    {
      "kind": "youtube#searchResult",
      "etag": "0uRnsHjgtajPGYeGmtzTXX8s230",
      "id": {
        "kind": "youtube#video",
        "videoId": "4PcL6-mjRNk"
      },
      "snippet": {
        "publishedAt": "2008-01-26T17:03:20Z",
        "channelId": "UChMQ-6G1heOGJLLx97KnFHQ",
        "title": "Jerry needs no help playing with his ball.",
        "description": "I built the ball machine because I thought my dog Jerry, might like it and that it would be something fun for me to build.  So after two years of on and off work, with many safety features such as IR proximity sensors to protect Jerry and my son from the machine, I finally complete.  \r\n\r\nFar from being a replacement for me, I was always right there with him enjoying his fun.  And with all the troubles that I went through to build the ball machine, I still end up throwing more balls than that the machine could count!  According to the computer, he played with the machine by himself only 3 times in his life.\r\n\r\nI recently put this video on YouTube to keep alive my earlier memories of him and (hopefully) provide some \"humorous distractions\" for anyone that might drop by.\r\n\r\nPlease enjoy the video.",
        "thumbnails": {
          "default": {
            "url": "https://i.ytimg.com/vi/4PcL6-mjRNk/default.jpg",
            "width": 120,
            "height": 90
          },
          "medium": {
            "url": "https://i.ytimg.com/vi/4PcL6-mjRNk/mqdefault.jpg",
            "width": 320,
            "height": 180
          },
          "high": {
            "url": "https://i.ytimg.com/vi/4PcL6-mjRNk/hqdefault.jpg",
            "width": 480,
            "height": 360
          }
        },
        "channelTitle": "lamgngo",
        "liveBroadcastContent": "none",
        "publishTime": "2008-01-26T17:03:20Z"
      }
    },
    {
      "kind": "youtube#searchResult",
      "etag": "lJ8y5sdm_BtYXaRTEg8zTkaUvEw",
      "id": {
        "kind": "youtube#video",
        "videoId": "r3wOdlOZYjE"
      },
      "snippet": {
        "publishedAt": "2017-05-15T14:13:12Z",
        "channelId": "UCY1Tr4l69GWoXipt5toSTFA",
        "title": "Bulldog Skater Otto - MADE VISIBLE by TCS",
        "description": "MADE VISIBLE ist ein Engagement des Touring Club Schweiz TCS für mehr Sichtbarkeit und Sicherheit im Strassenverkehr.\n\n▶▶▶ Website: https://madevisible.swiss\n▶▶▶ MADE VISIBLE Blog: https://madevisible.swiss/category/blog/\n▶▶▶ Facebook: https://www.facebook.com/madevisible.swiss/\n▶▶▶ Twitter: https://twitter.com/madevisible\n▶▶▶ Instagram: https://www.instagram.com/madevisible.swiss/\n\nOtto MADE VISIBLE, © TCS I Film: Joern Heitmann, Markenfilm Schweiz AG",
        "thumbnails": {
          "default": {
            "url": "https://i.ytimg.com/vi/r3wOdlOZYjE/default.jpg",
            "width": 120,
            "height": 90
          },
          "medium": {
            "url": "https://i.ytimg.com/vi/r3wOdlOZYjE/mqdefault.jpg",
            "width": 320,
            "height": 180
          },
          "high": {
            "url": "https://i.ytimg.com/vi/r3wOdlOZYjE/hqdefault.jpg",
            "width": 480,
            "height": 360
          },
          "standard": {
            "url": "https://i.ytimg.com/vi/r3wOdlOZYjE/sddefault.jpg",
            "width": 640,
            "height": 480
          }
        },
        "channelTitle": "MADE VISIBLE by TCS",
        "liveBroadcastContent": "none",
        "publishTime": "2017-05-15T14:13:12Z"
      }
    },
    {
      "kind": "youtube#searchResult",
      "etag": "Un53WgCvEL5cbHlUsj9G8_Tsxns",
      "id": {
        "kind": "youtube#video",
        "videoId": "qFDObDh67zs"
      },
      "snippet": {
        "publishedAt": "2019-11-15T04:18:09Z",
        "channelId": "UCRSDNqcqJR8m81-bVttpCCw",
        "title": "Skateboard Tricks That Look INSANE... (Skateboarding)",
        "description": "Skateboard Tricks That Look INSANE... (Skateboarding)\n\n👕 https://strictlyskateboard.com\n\n❤️ Strictly Skateboarding ❤️\n● Instagram: https://www.instagram.com/strictlysk8boarding\n● Facebook: https://www.facebook.com/strictlyskateboarding\n\nToday we've put together Skateboard Tricks That Look INSANE... Tricks down big stairs, Rails and Skateboarding gaps! Skaters in this video are from all around the world and different skill levels... Subscribe and Enjoy the video!\n\n#skateboard #tricks #skateboarding #skaters\n\nSimilar Videos:\n\nWhen SKATERS Go INSANE... 4\nhttps://youtu.be/RuS0nWccfE0\n\nWhen SKATERS Go INSANE... 3\nhttps://youtu.be/rkxzPTvmgl0\n\nWhen SKATERS Go INSANE... 2\nhttps://youtu.be/mJ7-H2fRk_o\n\nSkaters vs Ultimate Skateboarding Tricks! (Wins & Fails)\nhttps://youtu.be/fNmqIrtmOGs\n\nWhen SKATERS Go INSANE...\nhttps://youtu.be/hPS1b3cicfo\n\nPeople With Amazing Skateboarding Tricks! (Skaters)\nhttps://youtu.be/JZ5DEczJTLo\n\nSkateboarding Tricks You've Never Seen Before! (Skaters vs Tricks)\nhttps://youtu.be/guD60HLgEKg\n\nSkaters EXTREME Skateboarding 2019! (Wins & Fails)\nhttps://youtu.be/r8iOvj0m7hI\n\nThese People are INSANE! 2019 (Skateboarding)\nhttps://youtu.be/w12S-BYFwEM\n\nSkaters vs Scary Skateboarding Tricks! #2 (Wins & Fails)\nhttps://youtu.be/kbCmBYThGWI\n\nHere on Strictly Skateboarding we produce quality Skateboarding videos of Skaters from all around the World. With the main goal of making the best Skateboarding videos we possibly can that showcase all the different aspects that Skateboarding has to offer, Including: Impressive Tricks, Funny Moments and more...\n\nStrictly Skateboarding always has the Skaters permission to be featured in our videos.",
        "thumbnails": {
          "default": {
            "url": "https://i.ytimg.com/vi/qFDObDh67zs/default.jpg",
            "width": 120,
            "height": 90
          },
          "medium": {
            "url": "https://i.ytimg.com/vi/qFDObDh67zs/mqdefault.jpg",
            "width": 320,
            "height": 180
          },
          "high": {
            "url": "https://i.ytimg.com/vi/qFDObDh67zs/hqdefault.jpg",
            "width": 480,
            "height": 360
          },
          "standard": {
            "url": "https://i.ytimg.com/vi/qFDObDh67zs/sddefault.jpg",
            "width": 640,
            "height": 480
          },
          "maxres": {
            "url": "https://i.ytimg.com/vi/qFDObDh67zs/maxresdefault.jpg",
            "width": 1280,
            "height": 720
          }
        },
        "channelTitle": "Strictly Skateboarding",
        "liveBroadcastContent": "none",
        "publishTime": "2019-11-15T04:18:09Z"
      }
    },
    {
      "kind": "youtube#searchResult",
      "etag": "66C4zzFhmxTqqtJpWdh0PiQuWas",
      "id": {
        "kind": "youtube#video",
        "videoId": "OrJMUNEyZsE"
      },
      "snippet": {
        "publishedAt": "2018-09-13T16:33:31Z",
        "channelId": "UCYK1TyKyMxyDQU8c6zF8ltg",
        "title": "Funniest Videos for Pets to Watch Compilation | Funny Pet Videos",
        "description": "Do you like just putting on the TV and leave something for your pets to watch? Why not put on this 2 hour compilation of the funniest and cutest animals to leave your pets some company.\n\nWe love to bring you the best videos on the internet! Everything from Funny Videos, Fails, Fail Videos, Funny Baby Videos, TNTL Challenge, Si Te Ries Pierdes, Win Fail Fun, Funny Dogs, Makeup Tutorials and MORE! \n\nCheck out the ULTIMATE PLAYLIST here►https://www.youtube.com/playlist?list=PLnEgJF0UIKFC_ddIfDYI94vtY5cuWqDFk\n\nFunny Pet Videos brings you the best cute animal compilations, try not to laugh challenges, fails, wins, and hilarious viral videos.  We feature dogs, cats, horses, pigs, lions, lizards, rodents, bugs, spiders, tigers, kittens, puppies, squirrels, foxes, and more in the best new dank memes, funny clips, and you laugh you lose challenges and create collective of funny pets, life awesome moments, and epic wins.  \n\nNot content with only one platform, we’re committed to montages from Vine, Twitter, Instagram, Facebook, Snapchat, and Musically.  Sit back and enjoy a veritable fail army: kids fails, animal fails, girl fails, trampoline fails, car fails, on the job fails, old people fails, school fails, water fails, prank fails and pranks gone wrong, and more!  \n\nNot convinced? Check out some of our greatest hits below!\n\nFunniest Pet Reactions & Bloopers of January 2018 | Funny Pet Videos\nhttps://www.youtube.com/watch?v=Gc4OXzPY0Gg\n\nUltimate FUNNY DOG Compilation of 2017 | Funny Pet Videos\nhttps://www.youtube.com/watch?v=lIBQTZBRoC0\n\nFunniest Pet Reactions & Bloopers of November 2017 | Funny Pet Videos\nhttps://www.youtube.com/watch?v=8criqdtLGVI\n\nUltimate Cute Pets vs. Epic Kids Fails Compilation | Funny Pet Videos February 2018\nhttps://www.youtube.com/watch?v=CjMVtGsFULk\n\nTry Not To Laugh At This Ultimate Funny Dog Video Compilation | Funny Pet Videos\nhttps://www.youtube.com/watch?v=AcL0MeVZIxM\n\nBEST ANIMALS OF 2017 | Funny Pet Videos\nhttps://www.youtube.com/watch?v=34NjK6pRFiM\n\nTRY NOT TO LAUGH at FUNNY PET FAILS 2017 | Funny Pet Videos\nhttps://www.youtube.com/watch?v=A6hrw6KGdtM\n\nUltimate Try Not to Aww Compilation of 2017 | Funny Pet Videos\nhttps://www.youtube.com/watch?v=4WiXPFBwx7M\n\nFunniest Pet Reactions & Bloopers of August 2017 | Funny Pet Videos\nhttps://www.youtube.com/watch?v=Nz7eX19isF4\n\nFunniest Animals Scaring People Reactions of 2018 Weekly Compilation | Funny Pet Videos\nhttps://www.youtube.com/watch?v=8fspq-Ow-A8\n\nOur channel features content from: America’s Funniest Home Videos, Storyful, Launch Pad Entertainment LPE, VVUK, People Doing Things, and more!\n\nCheck out our partners! \n\nDumb Genius\nhttps://www.youtube.com/user/TheBestVines\n\nMusically Compilations\nhttps://www.youtube.com/channel/UC7SK2sk4YhfbJs57vBg3UbQ\n\nFunny Vines\nhttps://www.youtube.com/user/VineAholic\n\nThe Best Fails\nhttps://www.youtube.com/channel/UCuunebfqIi8uCzAs_fO1D6Q\n\nTry Not to Laugh Challenge\nhttps://www.youtube.com/channel/UCIDaoGGZ0VL_lWajKts4bww\n\nMas Supreme\nhttps://www.youtube.com/channel/UCrSB37ax8L3rZY3WtDMMitg\n\nLife Awesome\n\nTiger Productions / Tiger Funny Works\n\nCoVines / CoViners\n\n#funnypetvideos #funnydogs #animals #cutecats",
        "thumbnails": {
          "default": {
            "url": "https://i.ytimg.com/vi/OrJMUNEyZsE/default.jpg",
            "width": 120,
            "height": 90
          },
          "medium": {
            "url": "https://i.ytimg.com/vi/OrJMUNEyZsE/mqdefault.jpg",
            "width": 320,
            "height": 180
          },
          "high": {
            "url": "https://i.ytimg.com/vi/OrJMUNEyZsE/hqdefault.jpg",
            "width": 480,
            "height": 360
          },
          "standard": {
            "url": "https://i.ytimg.com/vi/OrJMUNEyZsE/sddefault.jpg",
            "width": 640,
            "height": 480
          },
          "maxres": {
            "url": "https://i.ytimg.com/vi/OrJMUNEyZsE/maxresdefault.jpg",
            "width": 1280,
            "height": 720
          }
        },
        "channelTitle": "Funny Pet Videos",
        "liveBroadcastContent": "none",
        "publishTime": "2018-09-13T16:33:31Z"
      }
    },
    {
      "kind": "youtube#searchResult",
      "etag": "7GWb18qlPMO3rwTamVjeAm6-6tw",
      "id": {
        "kind": "youtube#video",
        "videoId": "UDEN_aDkWLA"
      },
      "snippet": {
        "publishedAt": "2018-08-24T20:48:45Z",
        "channelId": "UCYK1TyKyMxyDQU8c6zF8ltg",
        "title": "Funniest Confused Pets Compilation 2018 | Funny Pet Videos",
        "description": "We love to bring you the best videos on the internet! Everything from Funny Videos, Fails, Fail Videos, Funny Baby Videos, TNTL Challenge, Si Te Ries Pierdes, Win Fail Fun, Funny Dogs, Makeup Tutorials and MORE! \n\nCheck out the ULTIMATE PLAYLIST here►https://www.youtube.com/playlist?list=PLnEgJF0UIKFC_ddIfDYI94vtY5cuWqDFk\n\nFunny Pet Videos brings you the best cute animal compilations, try not to laugh challenges, fails, wins, and hilarious viral videos.  We feature dogs, cats, horses, pigs, lions, lizards, rodents, bugs, spiders, tigers, kittens, puppies, squirrels, foxes, and more in the best new dank memes, funny clips, and you laugh you lose challenges and create collective of funny pets, life awesome moments, and epic wins.  \n\nNot content with only one platform, we’re committed to montages from Vine, Twitter, Instagram, Facebook, Snapchat, and Musically.  Sit back and enjoy a veritable fail army: kids fails, animal fails, girl fails, trampoline fails, car fails, on the job fails, old people fails, school fails, water fails, prank fails and pranks gone wrong, and more!  \n\nNot convinced? Check out some of our greatest hits below!\n\nFunniest Pet Reactions & Bloopers of January 2018 | Funny Pet Videos\nhttps://www.youtube.com/watch?v=Gc4OXzPY0Gg\n\nUltimate FUNNY DOG Compilation of 2017 | Funny Pet Videos\nhttps://www.youtube.com/watch?v=lIBQTZBRoC0\n\nFunniest Pet Reactions & Bloopers of November 2017 | Funny Pet Videos\nhttps://www.youtube.com/watch?v=8criqdtLGVI\n\nUltimate Cute Pets vs. Epic Kids Fails Compilation | Funny Pet Videos February 2018\nhttps://www.youtube.com/watch?v=CjMVtGsFULk\n\nTry Not To Laugh At This Ultimate Funny Dog Video Compilation | Funny Pet Videos\nhttps://www.youtube.com/watch?v=AcL0MeVZIxM\n\nBEST ANIMALS OF 2017 | Funny Pet Videos\nhttps://www.youtube.com/watch?v=34NjK6pRFiM\n\nTRY NOT TO LAUGH at FUNNY PET FAILS 2017 | Funny Pet Videos\nhttps://www.youtube.com/watch?v=A6hrw6KGdtM\n\nUltimate Try Not to Aww Compilation of 2017 | Funny Pet Videos\nhttps://www.youtube.com/watch?v=4WiXPFBwx7M\n\nFunniest Pet Reactions & Bloopers of August 2017 | Funny Pet Videos\nhttps://www.youtube.com/watch?v=Nz7eX19isF4\n\nFunniest Animals Scaring People Reactions of 2018 Weekly Compilation | Funny Pet Videos\nhttps://www.youtube.com/watch?v=8fspq-Ow-A8\n\nOur channel features content from: America’s Funniest Home Videos, Storyful, Launch Pad Entertainment LPE, VVUK, People Doing Things, and more!\n\nCheck out our partners! \n\nDumb Genius\nhttps://www.youtube.com/user/TheBestVines\n\nMusically Compilations\nhttps://www.youtube.com/channel/UC7SK2sk4YhfbJs57vBg3UbQ\n\nFunny Vines\nhttps://www.youtube.com/user/VineAholic\n\nThe Best Fails\nhttps://www.youtube.com/channel/UCuunebfqIi8uCzAs_fO1D6Q\n\nTry Not to Laugh Challenge\nhttps://www.youtube.com/channel/UCIDaoGGZ0VL_lWajKts4bww\n\nMas Supreme\nhttps://www.youtube.com/channel/UCrSB37ax8L3rZY3WtDMMitg\n\nLife Awesome\n\nTiger Productions / Tiger Funny Works\n\nCoVines / CoViners\n\n#funnypetvideos #funnydogs #animals #cutecats",
        "thumbnails": {
          "default": {
            "url": "https://i.ytimg.com/vi/UDEN_aDkWLA/default.jpg",
            "width": 120,
            "height": 90
          },
          "medium": {
            "url": "https://i.ytimg.com/vi/UDEN_aDkWLA/mqdefault.jpg",
            "width": 320,
            "height": 180
          },
          "high": {
            "url": "https://i.ytimg.com/vi/UDEN_aDkWLA/hqdefault.jpg",
            "width": 480,
            "height": 360
          },
          "standard": {
            "url": "https://i.ytimg.com/vi/UDEN_aDkWLA/sddefault.jpg",
            "width": 640,
            "height": 480
          },
          "maxres": {
            "url": "https://i.ytimg.com/vi/UDEN_aDkWLA/maxresdefault.jpg",
            "width": 1280,
            "height": 720
          }
        },
        "channelTitle": "Funny Pet Videos",
        "liveBroadcastContent": "none",
        "publishTime": "2018-08-24T20:48:45Z"
      }
    },
    {
      "kind": "youtube#searchResult",
      "etag": "eQed39wQJ6vGCmZwaZTdONdM4uc",
      "id": {
        "kind": "youtube#video",
        "videoId": "pbNwJcnsLDg"
      },
      "snippet": {
        "publishedAt": "2016-05-20T09:40:48Z",
        "channelId": "UCLysNmJdUrvUwmNFfo1eSLA",
        "title": "Skateboarding dog in Clissold Park",
        "description": "",
        "thumbnails": {
          "default": {
            "url": "https://i.ytimg.com/vi/pbNwJcnsLDg/default.jpg",
            "width": 120,
            "height": 90
          },
          "medium": {
            "url": "https://i.ytimg.com/vi/pbNwJcnsLDg/mqdefault.jpg",
            "width": 320,
            "height": 180
          },
          "high": {
            "url": "https://i.ytimg.com/vi/pbNwJcnsLDg/hqdefault.jpg",
            "width": 480,
            "height": 360
          },
          "standard": {
            "url": "https://i.ytimg.com/vi/pbNwJcnsLDg/sddefault.jpg",
            "width": 640,
            "height": 480
          },
          "maxres": {
            "url": "https://i.ytimg.com/vi/pbNwJcnsLDg/maxresdefault.jpg",
            "width": 1280,
            "height": 720
          }
        },
        "channelTitle": "Simon de Deney",
        "liveBroadcastContent": "none",
        "publishTime": "2016-05-20T09:40:48Z"
      }
    },
    {
      "kind": "youtube#searchResult",
      "etag": "P1vC5VKKskQDlG2pmNuusD-4Gsg",
      "id": {
        "kind": "youtube#video",
        "videoId": "bzt4wGYq4ZA"
      },
      "snippet": {
        "publishedAt": "2013-12-28T19:29:45Z",
        "channelId": "UCtcUjp-Gaz2LjI8AfEA0Liw",
        "title": "Summer Loving for Tillman the Skateboarding and Surfing BullDog",
        "description": "CNN PRODUCER NOTE     It is ChrisMorrow's fourth year covering the annual Surf Dog Competition held in Imperial Beach, California, on June 22. She photographed Tillman, surfing through the waves. 'What's better than surfing dogs? I have two small rescue [dogs] and if they loved water, I would get them on a board,' she said.   http://ireport.cnn.com/docs/DOC-993209\n\n-------------------------------\n\nTillman, the English bulldog made famous on YouTube for his amazing skateboarding skills was catching waves today and competing at the Loews Surf Dog Competition - Unleashed by Petco.\n\n \n\nCheck out my video and photos from Imperial Beach and see how Tillman rings in summer!\n\n \n\nMy other iReports http://ireport.cnn.com/people/ChrisMorrow\n\n \n\nMy Twitter https://twitter.com/morrowchris",
        "thumbnails": {
          "default": {
            "url": "https://i.ytimg.com/vi/bzt4wGYq4ZA/default.jpg",
            "width": 120,
            "height": 90
          },
          "medium": {
            "url": "https://i.ytimg.com/vi/bzt4wGYq4ZA/mqdefault.jpg",
            "width": 320,
            "height": 180
          },
          "high": {
            "url": "https://i.ytimg.com/vi/bzt4wGYq4ZA/hqdefault.jpg",
            "width": 480,
            "height": 360
          },
          "standard": {
            "url": "https://i.ytimg.com/vi/bzt4wGYq4ZA/sddefault.jpg",
            "width": 640,
            "height": 480
          }
        },
        "channelTitle": "popularbox",
        "liveBroadcastContent": "none",
        "publishTime": "2013-12-28T19:29:45Z"
      }
    },
    {
      "kind": "youtube#searchResult",
      "etag": "-NrOKY_tERJS8jKKoIJ-yiSK2ZQ",
      "id": {
        "kind": "youtube#video",
        "videoId": "skVGR9I0lWA"
      },
      "snippet": {
        "publishedAt": "2019-01-11T23:29:44Z",
        "channelId": "UCqC9wT9TI5Va0yWG77-q3IA",
        "title": "George the skateboarding dog",
        "description": "George is a five-year-old English Bulldog on Bainbridge Island who loves to skateboard. \"We can't even say the word 'skateboard' in the house,\" says owner Marcus Singel. (Ellen M. Banner and Corinne Chin / The Seattle Times)",
        "thumbnails": {
          "default": {
            "url": "https://i.ytimg.com/vi/skVGR9I0lWA/default.jpg",
            "width": 120,
            "height": 90
          },
          "medium": {
            "url": "https://i.ytimg.com/vi/skVGR9I0lWA/mqdefault.jpg",
            "width": 320,
            "height": 180
          },
          "high": {
            "url": "https://i.ytimg.com/vi/skVGR9I0lWA/hqdefault.jpg",
            "width": 480,
            "height": 360
          },
          "standard": {
            "url": "https://i.ytimg.com/vi/skVGR9I0lWA/sddefault.jpg",
            "width": 640,
            "height": 480
          },
          "maxres": {
            "url": "https://i.ytimg.com/vi/skVGR9I0lWA/maxresdefault.jpg",
            "width": 1280,
            "height": 720
          }
        },
        "channelTitle": "seattletimesdotcom",
        "liveBroadcastContent": "none",
        "publishTime": "2019-01-11T23:29:44Z"
      }
    },
    {
      "kind": "youtube#searchResult",
      "etag": "A_Gz_yYICr8PaLVPqGmgFJqebgU",
      "id": {
        "kind": "youtube#video",
        "videoId": "AcL0MeVZIxM"
      },
      "snippet": {
        "publishedAt": "2018-03-20T16:50:55Z",
        "channelId": "UCYK1TyKyMxyDQU8c6zF8ltg",
        "title": "Try Not To Laugh At This Ultimate Funny Dog Video Compilation | Funny Pet Videos",
        "description": "Brand new weekly theme compilation where we challenge you to Try Not To Laugh at these Funny Dogs. \n\nFunny Pet Videos brings you the best cute animal compilations, try not to laugh challenges, fails, wins, and hilarious viral videos.  We feature dogs, cats, horses, pigs, lions, lizards, rodents, bugs, spiders, tigers, kittens, puppies, squirrels, foxes, and more in the best new dank memes, funny clips, and you laugh you lose challenges and create collective of funny pets, life awesome moments, and epic wins.  \n\nNot content with only one platform, we’re committed to montages from Vine, Twitter, Instagram, Facebook, Snapchat, and Musically.  Sit back and enjoy a veritable fail army: kids fails, animal fails, girl fails, trampoline fails, car fails, on the job fails, old people fails, school fails, water fails, prank fails and pranks gone wrong, and more!  \n\nNot convinced? Check out some of our greatest hits below!\n\nFunniest Pet Reactions & Bloopers of January 2018 | Funny Pet Videos\nhttps://www.youtube.com/watch?v=Gc4OXzPY0Gg\n\nUltimate FUNNY DOG Compilation of 2017 | Funny Pet Videos\nhttps://www.youtube.com/watch?v=lIBQTZBRoC0\n\nFunniest Pet Reactions & Bloopers of November 2017 | Funny Pet Videos\nhttps://www.youtube.com/watch?v=8criqdtLGVI\n\nUltimate Cute Pets vs. Epic Kids Fails Compilation | Funny Pet Videos February 2018\nhttps://www.youtube.com/watch?v=CjMVtGsFULk\n\nTry Not To Laugh At This Ultimate Funny Dog Video Compilation | Funny Pet Videos\nhttps://www.youtube.com/watch?v=AcL0MeVZIxM\n\nBEST ANIMALS OF 2017 | Funny Pet Videos\nhttps://www.youtube.com/watch?v=34NjK6pRFiM\n\nTRY NOT TO LAUGH at FUNNY PET FAILS 2017 | Funny Pet Videos\nhttps://www.youtube.com/watch?v=A6hrw6KGdtM\n\nUltimate Try Not to Aww Compilation of 2017 | Funny Pet Videos\nhttps://www.youtube.com/watch?v=4WiXPFBwx7M\n\nFunniest Pet Reactions & Bloopers of August 2017 | Funny Pet Videos\nhttps://www.youtube.com/watch?v=Nz7eX19isF4\n\nFunniest Animals Scaring People Reactions of 2018 Weekly Compilation | Funny Pet Videos\nhttps://www.youtube.com/watch?v=8fspq-Ow-A8\n\nOur channel features content from: America’s Funniest Home Videos, Storyful, Launch Pad Entertainment LPE, VVUK,  People Doing Things, and more!\n\nCheck out our partners! \n\nDumb Genius\nhttps://www.youtube.com/user/TheBestVines\n\nMusically Compilations\nhttps://www.youtube.com/channel/UC7SK2sk4YhfbJs57vBg3UbQ\n\nFunny Vines\nhttps://www.youtube.com/user/VineAholic\n\nThe Best Fails\nhttps://www.youtube.com/channel/UCuunebfqIi8uCzAs_fO1D6Q\n\nTry Not to Laugh Challenge\nhttps://www.youtube.com/channel/UCIDaoGGZ0VL_lWajKts4bww\n\nMas Supreme\nhttps://www.youtube.com/channel/UCrSB37ax8L3rZY3WtDMMitg\n\nLife Awesome\n\nTiger Productions / Tiger Funny Works\n\nCoVines / CoViners\n\n#funnypetvideos #funnydogs #animals #cutecats #funnypetvideso #fpv #animals #funnydogs #cutecats",
        "thumbnails": {
          "default": {
            "url": "https://i.ytimg.com/vi/AcL0MeVZIxM/default.jpg",
            "width": 120,
            "height": 90
          },
          "medium": {
            "url": "https://i.ytimg.com/vi/AcL0MeVZIxM/mqdefault.jpg",
            "width": 320,
            "height": 180
          },
          "high": {
            "url": "https://i.ytimg.com/vi/AcL0MeVZIxM/hqdefault.jpg",
            "width": 480,
            "height": 360
          },
          "standard": {
            "url": "https://i.ytimg.com/vi/AcL0MeVZIxM/sddefault.jpg",
            "width": 640,
            "height": 480
          },
          "maxres": {
            "url": "https://i.ytimg.com/vi/AcL0MeVZIxM/maxresdefault.jpg",
            "width": 1280,
            "height": 720
          }
        },
        "channelTitle": "Funny Pet Videos",
        "liveBroadcastContent": "none",
        "publishTime": "2018-03-20T16:50:55Z"
      }
    },
    {
      "kind": "youtube#searchResult",
      "etag": "MjF2hVKigaIVNF0Xr3IJ5UVgmao",
      "id": {
        "kind": "youtube#video",
        "videoId": "gdJhY3iLUTQ"
      },
      "snippet": {
        "publishedAt": "2018-12-15T13:40:43Z",
        "channelId": "UCPQSVmzeEg9pBdrB2udaT1w",
        "title": "Amazing French Bulldog Rocks On Skateboard",
        "description": "Enjoying night with skateboarding 🤩🐶🤩\n\n• Video from Tik Tok (ID: 120793055)\n\n• Subscribe To Get Your Daily Dose Of Cuteness:\nhttps://www.youtube.com/ViralPaws?sub_confirmation=1 ( 🔔 Make sure to turn the notification bell on! 🔔)\n\n• Follow and Like us on Social Media:\n📘 Facebook: https://facebook.com/viralpaws\n📷 Instagram: https://instagram.com/viralpaws\n🐦 Twitter: https://twitter.com/viralpaws\n\n• Music: Ikson - Stardust (https://soundcloud.com/ikson)\n\n• Copyright Issues or Lack of Credits? Please feel free to contact us by email or by Facebook/IG message. We will response and get it resolved within 24Hrs.\n\n• We donate and support Animal Shelters!\n\n• All rights belong to it's rightful owner/owner's, I do not own this video nor the image featured in the video.\n\n📋 Tags : #FrenchBullDog #SkateboardingDog #Frenchie",
        "thumbnails": {
          "default": {
            "url": "https://i.ytimg.com/vi/gdJhY3iLUTQ/default.jpg",
            "width": 120,
            "height": 90
          },
          "medium": {
            "url": "https://i.ytimg.com/vi/gdJhY3iLUTQ/mqdefault.jpg",
            "width": 320,
            "height": 180
          },
          "high": {
            "url": "https://i.ytimg.com/vi/gdJhY3iLUTQ/hqdefault.jpg",
            "width": 480,
            "height": 360
          },
          "standard": {
            "url": "https://i.ytimg.com/vi/gdJhY3iLUTQ/sddefault.jpg",
            "width": 640,
            "height": 480
          },
          "maxres": {
            "url": "https://i.ytimg.com/vi/gdJhY3iLUTQ/maxresdefault.jpg",
            "width": 1280,
            "height": 720
          }
        },
        "channelTitle": "Viral Paws",
        "liveBroadcastContent": "none",
        "publishTime": "2018-12-15T13:40:43Z"
      }
    },
    {
      "kind": "youtube#searchResult",
      "etag": "mLLERfZqfOiX6TTSMsjc1RpbcSo",
      "id": {
        "kind": "youtube#video",
        "videoId": "XTKc3X2ZLfE"
      },
      "snippet": {
        "publishedAt": "2016-01-03T20:30:03Z",
        "channelId": "UCVew-Ft8yf_CpfBOjMZO0Sg",
        "title": "Bulldogs love Skateboards! Bulldogs are the best Skateboarding Dogs ever!",
        "description": "In this Bulldog compilation you will find some of the cutest Bulldog Skateboarders. \nEnjoy this funny and cute video and please leave a comment if you like my compilation.\nIf you like my cute video please share and like it and subscribe for more funny stuff :)",
        "thumbnails": {
          "default": {
            "url": "https://i.ytimg.com/vi/XTKc3X2ZLfE/default.jpg",
            "width": 120,
            "height": 90
          },
          "medium": {
            "url": "https://i.ytimg.com/vi/XTKc3X2ZLfE/mqdefault.jpg",
            "width": 320,
            "height": 180
          },
          "high": {
            "url": "https://i.ytimg.com/vi/XTKc3X2ZLfE/hqdefault.jpg",
            "width": 480,
            "height": 360
          },
          "standard": {
            "url": "https://i.ytimg.com/vi/XTKc3X2ZLfE/sddefault.jpg",
            "width": 640,
            "height": 480
          },
          "maxres": {
            "url": "https://i.ytimg.com/vi/XTKc3X2ZLfE/maxresdefault.jpg",
            "width": 1280,
            "height": 720
          }
        },
        "channelTitle": "Emily the Bulldog",
        "liveBroadcastContent": "none",
        "publishTime": "2016-01-03T20:30:03Z"
      }
    },
    {
      "kind": "youtube#searchResult",
      "etag": "3s8_h2h2ZhJfMDrhruVdsMAWg-4",
      "id": {
        "kind": "youtube#video",
        "videoId": "zzIdL8UAXeQ"
      },
      "snippet": {
        "publishedAt": "2015-11-01T17:34:52Z",
        "channelId": "UCVT1tPkR-fUVlO652EcO3ow",
        "title": "Remembering Tillman, the skateboarding bulldog",
        "description": "His exploits were legendary: Tillman, the skateboarding bulldog, a Guinness World Record-holder, was known for his high-velocity videos that were Internet favorites. Charles Osgood pays tribute to the sporty canine, who passed away this week at the age of 10.",
        "thumbnails": {
          "default": {
            "url": "https://i.ytimg.com/vi/zzIdL8UAXeQ/default.jpg",
            "width": 120,
            "height": 90
          },
          "medium": {
            "url": "https://i.ytimg.com/vi/zzIdL8UAXeQ/mqdefault.jpg",
            "width": 320,
            "height": 180
          },
          "high": {
            "url": "https://i.ytimg.com/vi/zzIdL8UAXeQ/hqdefault.jpg",
            "width": 480,
            "height": 360
          },
          "standard": {
            "url": "https://i.ytimg.com/vi/zzIdL8UAXeQ/sddefault.jpg",
            "width": 640,
            "height": 480
          }
        },
        "channelTitle": "CBS Sunday Morning",
        "liveBroadcastContent": "none",
        "publishTime": "2015-11-01T17:34:52Z"
      }
    }
  ]
}
